setup.py
Test/CommonTest.py
Test/DateTest.py
Test/HashTest.py
Test/ImageTest.py
Test/SystemTest.py
Test/WebTest.py
Test/__init__.py
common_toolbox.egg-info/PKG-INFO
common_toolbox.egg-info/SOURCES.txt
common_toolbox.egg-info/dependency_links.txt
common_toolbox.egg-info/not-zip-safe
common_toolbox.egg-info/requires.txt
common_toolbox.egg-info/top_level.txt
toolbox/Common.py
toolbox/Date.py
toolbox/Hash.py
toolbox/Image.py
toolbox/MongoUtils.py
toolbox/MysqlUtils.py
toolbox/System.py
toolbox/Web.py
toolbox/__init__.py