Metadata-Version: 1.0
Name: common-toolbox
Version: 0.0.12
Summary: A python toolbox contains several function you might need
Home-page: https://github.com/nmghr9/CommonToolBox
Author: Henry Hou
Author-email: nmghr9@gmail.com
License: MIT
Platform: UNKNOWN
